orch/__about__.py
orch/__init__.py
orch-0.0.2.dist-info/METADATA
orch-0.0.2.dist-info/WHEEL
orch-0.0.2.dist-info/licenses/LICENSE
orch-0.0.2.dist-info/RECORD
